<?xml version="1.0" encoding="UTF-8"?><FDSNStationXML xmlns="http://www.fdsn.org/xml/station/1" schemaVersion="1.2"><Source>SeisComP</Source><Sender>KOERI</Sender><Created>2024-08-13T12:52:02.802711Z</Created><Network code="KO" startDate="1971-01-01T00:00:00Z" restrictedStatus="open"><Description>Kandilli Observatory (KO) Regional Seismic Network</Description><Identifier type="DOI">10.7914/SN/KO</Identifier><Station code="ADVT" startDate="2006-05-19T00:00:00Z" restrictedStatus="open"><Latitude>40.4332</Latitude><Longitude>29.7383</Longitude><Elevation>193</Elevation><Site><Name>Abdulvahap, Iznik, Bursa, Turkiye</Name></Site><CreationDate>2006-05-19T00:00:00Z</CreationDate></Station></Network></FDSNStationXML>
